gerritaction/__init__.py
gerritaction/__version__.py
gerritaction/main.py
gerritaction/action/__init__.py
gerritaction/action/action.py
gerritaction/cmd/__init__.py
gerritaction/cmd/argument.py
gerritaction/cmd/banner.py
gerritaction/config/__init__.py
gerritaction/config/config.py
gerritaction/gerrit/__init__.py
gerritaction/gerrit/gerrit.py
gerritaction/logger/__init__.py
gerritaction/logger/logger.py
gerritaction/proto/__init__.py
gerritaction/proto/proto.py
gerritaction-1.11.0.dist-info/LICENSE
gerritaction-1.11.0.dist-info/METADATA
gerritaction-1.11.0.dist-info/WHEEL
gerritaction-1.11.0.dist-info/entry_points.txt
gerritaction-1.11.0.dist-info/top_level.txt
gerritaction-1.11.0.dist-info/RECORD
