Metadata-Version: 2.1
Name: gerritaction
Version: 1.11.0
Summary: Gerrit Action
Home-page: https://github.com/craftslab/gerritaction
Download-URL: https://github.com/craftslab/gerritaction/archive/v1.11.0.tar.gz
Author: Jia Jia
Author-email: angersax@sina.com
License: Apache-2.0
Keywords: gerrit,action
Classifier: Development Status :: 3 - Alpha
Classifier: Intended Audience :: Developers
Classifier: Programming Language :: Python :: 3
Classifier: License :: OSI Approved :: Apache Software License
Classifier: Operating System :: OS Independent
License-File: LICENSE
Requires-Dist: black
Requires-Dist: colorama
Requires-Dist: coverage
Requires-Dist: coveralls
Requires-Dist: flake8
Requires-Dist: hypothesis
Requires-Dist: mypy
Requires-Dist: pre-commit
Requires-Dist: pytest
Requires-Dist: requests
Requires-Dist: setuptools
Requires-Dist: twine
Requires-Dist: wheel
